atlassian_doc_builder/__init__.py
atlassian_doc_builder/adf_content_node.py
atlassian_doc_builder/adf_marks.py
atlassian_doc_builder/adf_object.py
atlassian_doc_builder/adf_simple.py
atlassian_doc_builder/adf_table.py
atlassian_doc_builder-0.5.2.dist-info/licenses/LICENSE
atlassian_doc_builder-0.5.2.dist-info/METADATA
atlassian_doc_builder-0.5.2.dist-info/WHEEL
atlassian_doc_builder-0.5.2.dist-info/top_level.txt
atlassian_doc_builder-0.5.2.dist-info/RECORD
