Metadata-Version: 2.4
Name: atlassian-doc-builder
Version: 0.5.2
Summary: Creating Atlassian Document in a programmatic way.
Author-email: khwong-c <kin.hin.wong.c@gmail.com>
License: MIT License
Project-URL: Repository, https://github.com/khwong-c/atlassian-doc-builder
Classifier: Development Status :: 4 - Beta
Classifier: License :: OSI Approved :: MIT License
Classifier: Programming Language :: Python
Classifier: Programming Language :: Python :: 3
Requires-Python: >=3.8
License-File: LICENSE
Requires-Dist: jsonschema
Dynamic: license-file
